polkadot_contract_sdk/__init__.py
polkadot_contract_sdk/cli.py
polkadot_contract_sdk/deploy.py
polkadot_contract_sdk/interact.py
polkadot_contract_sdk-1.0.0.dist-info/licenses/LICENSE
polkadot_contract_sdk-1.0.0.dist-info/METADATA
polkadot_contract_sdk-1.0.0.dist-info/WHEEL
polkadot_contract_sdk-1.0.0.dist-info/entry_points.txt
polkadot_contract_sdk-1.0.0.dist-info/top_level.txt
polkadot_contract_sdk-1.0.0.dist-info/RECORD
