Metadata-Version: 2.4
Name: polkadot-contract-sdk
Version: 1.0.0
Summary: SDK for deploying and interacting with smart contracts on Polkadot/Kusama networks
Home-page: https://github.com/Omkar-Ghongade/polkadot-contract-sdk
Author: Omkar Ghongade
Author-email: Omkar Ghongade <the21og.work@gmail.com>
License-Expression: MIT
Project-URL: Homepage, https://github.com/Omkar-Ghongade/polkadot-contract-sdk
Project-URL: Documentation, https://github.com/Omkar-Ghongade/polkadot-contract-sdk#readme
Project-URL: Repository, https://github.com/Omkar-Ghongade/polkadot-contract-sdk
Project-URL: Issues, https://github.com/Omkar-Ghongade/polkadot-contract-sdk/issues
Keywords: polkadot,kusama,blockchain,smart-contracts,web3,ethereum
Classifier: Development Status :: 4 - Beta
Classifier: Intended Audience :: Developers
Classifier: Programming Language :: Python :: 3
Classifier: Programming Language :: Python :: 3.8
Classifier: Programming Language :: Python :: 3.9
Classifier: Programming Language :: Python :: 3.10
Classifier: Programming Language :: Python :: 3.11
Classifier: Programming Language :: Python :: 3.12
Classifier: Topic :: Software Development :: Libraries :: Python Modules
Requires-Python: >=3.8
License-File: LICENSE
Requires-Dist: web3>=6.0.0
Requires-Dist: py-solc-x>=1.1.1
Requires-Dist: python-dotenv>=1.0.0
Dynamic: author
Dynamic: home-page
Dynamic: license-file
Dynamic: requires-python
